podcast2notion/__init__.py
podcast2notion/__main__.py
podcast2notion/config.py
podcast2notion/notion_helper.py
podcast2notion/podcast.py
podcast2notion/speech_text.py
podcast2notion/update_heatmap.py
podcast2notion/utils.py
podcast2notion-0.2.5.dist-info/METADATA
podcast2notion-0.2.5.dist-info/WHEEL
podcast2notion-0.2.5.dist-info/entry_points.txt
podcast2notion-0.2.5.dist-info/top_level.txt
podcast2notion-0.2.5.dist-info/RECORD
