Metadata-Version: 2.1
Name: podcast2notion
Version: 0.2.5
Summary: 自动将习惯同步到Notion
Home-page: https://github.com/malinkang/podcast2notionpro
Author: malinkang
Author-email: linkang.ma@gmail.com
Classifier: Programming Language :: Python :: 3
Classifier: License :: OSI Approved :: MIT License
Classifier: Operating System :: OS Independent
Requires-Python: >=3.6
Requires-Dist: requests
Requires-Dist: pendulum
Requires-Dist: retrying
Requires-Dist: notion-client
Requires-Dist: github-heatmap
Requires-Dist: python-dotenv
Requires-Dist: emoji
